rayexec-0.0.122.dist-info/METADATA
rayexec-0.0.122.dist-info/WHEEL
rayexec/__init__.py
rayexec/rayexec.abi3.so
rayexec-0.0.122.dist-info/RECORD
