Metadata-Version: 2.4
Name: rayexec
Version: 0.0.122
Classifier: Programming Language :: Rust
Classifier: Programming Language :: Python :: Implementation :: CPython
Classifier: Programming Language :: Python :: Implementation :: PyPy
Summary: Next engine for GlareDB
Requires-Python: >=3.7
Project-URL: Homepage, https://glaredb.com
